gbq/__init__.py
gbq/bigquery.py
gbq/dto.py
gbq/exceptions.py
gbq/helpers.py
gbq/py.typed
gbq-1.0.5.dist-info/METADATA
gbq-1.0.5.dist-info/WHEEL
gbq-1.0.5.dist-info/licenses/LICENSE
gbq-1.0.5.dist-info/RECORD
