Metadata-Version: 2.1
Name: gbq
Version: 1.0.5
Summary: Python wrapper for interacting Google BigQuery.
Project-URL: Homepage, https://github.com/wayfair-incubator/gbq
Project-URL: changelog, https://github.com/wayfair-incubator/gbq/blob/main/CHANGELOG.md
Project-URL: issues, https://github.com/wayfair-incubator/gbq/issues
Project-URL: documentation, https://wayfair-incubator.github.io/gbq
Author-email: Jash Parekh <jparekh1@wayfair.com>
License: MIT
License-File: LICENSE
Classifier: Development Status :: 4 - Beta
Classifier: License :: OSI Approved :: MIT License
Classifier: Programming Language :: Python
Classifier: Programming Language :: Python :: 3
Classifier: Programming Language :: Python :: 3.8
Classifier: Programming Language :: Python :: 3.9
Classifier: Programming Language :: Python :: 3.10
Classifier: Programming Language :: Python :: 3.11
Classifier: Programming Language :: Python :: 3.12
Requires-Python: >=3.8
Requires-Dist: google-cloud-bigquery
Requires-Dist: pydantic<3,>=2.4.0
